example/Demo.py
example/__init__.py
md2xmind/Md2Xmind.py
md2xmind/__init__.py
md2xmind-1.2.3.dist-info/LICENSE
md2xmind-1.2.3.dist-info/METADATA
md2xmind-1.2.3.dist-info/WHEEL
md2xmind-1.2.3.dist-info/top_level.txt
md2xmind-1.2.3.dist-info/RECORD
